README.md
setup.py
bin/equipdb_gsheet_backup.py
bin/equipdb_rancid_audit.py
bin/get_al_port_data.py
umnet_scripts/__init__.py
umnet_scripts/constants.py
umnet_scripts/cyberark.py
umnet_scripts/googlesheet.py
umnet_scripts/rancid.py
umnet_scripts/umnetdb.py
umnet_scripts/umnetdisco.py
umnet_scripts/umnetequip.py
umnet_scripts/umnetinfo.py
umnet_scripts/umnetlb.py
umnet_scripts/umnetnso_restconf.py
umnet_scripts/utils.py
umnet_scripts.egg-info/PKG-INFO
umnet_scripts.egg-info/SOURCES.txt
umnet_scripts.egg-info/dependency_links.txt
umnet_scripts.egg-info/requires.txt
umnet_scripts.egg-info/top_level.txt