Metadata-Version: 2.1
Name: umnet_scripts
Version: 1.1.0
Summary: Python tools for interacting with UMnet's network tools
Home-page: https://gitlab.umich.edu/its-inf-net/umnet-scripts
Author: University of Michigan
Author-email: amylieb@umich.edu
Classifier: Programming Language :: Python :: 3
Classifier: Operating System :: OS Independent
Requires-Python: >=3.6
Requires-Dist: dnspython
Requires-Dist: regex
Requires-Dist: psycopg2-binary
Requires-Dist: sqlalchemy>=1.4
Requires-Dist: pynetbox
Requires-Dist: oracledb
Requires-Dist: ncclient
Requires-Dist: python-decouple
Requires-Dist: requests
Requires-Dist: urllib3
Requires-Dist: gspread
Requires-Dist: oauth2client
Requires-Dist: fabric
Requires-Dist: invoke<2.1
Requires-Dist: f5-sdk
